spatialfriend/__init__.py
spatialfriend/spatialfriend.py
spatialfriend-0.0.10.dist-info/LICENSE
spatialfriend-0.0.10.dist-info/METADATA
spatialfriend-0.0.10.dist-info/WHEEL
spatialfriend-0.0.10.dist-info/top_level.txt
spatialfriend-0.0.10.dist-info/RECORD
