Metadata-Version: 2.1
Name: spatialfriend
Version: 0.0.10
Summary: Python library for calculating geospatial data from gps coordinates.
Home-page: https://github.com/aaron-schroeder/spatialfriend
Author: Aaron Schroeder
Author-email: aaron@trailzealot.com
License: MIT License
Platform: UNKNOWN
Classifier: Programming Language :: Python :: 3.6
Classifier: License :: OSI Approved :: MIT License
Requires-Dist: geopy (>=1.20.0)
Requires-Dist: googlemaps (>=3.0)
Requires-Dist: numpy (>=1.14)
Requires-Dist: pandas (>=0.24)
Requires-Dist: scipy (>=1.1)
Provides-Extra: img
Requires-Dist: GDAL (>=2.1.4) ; extra == 'img'
Requires-Dist: utm (>=0.4.2) ; extra == 'img'
Provides-Extra: tnm
Requires-Dist: requests (>=2.22) ; extra == 'tnm'
Requires-Dist: urllib3 (>=1.25.6) ; extra == 'tnm'
